patchpy.py
patchpy-2.0.4.dist-info/METADATA
patchpy-2.0.4.dist-info/WHEEL
patchpy-2.0.4.dist-info/entry_points.txt
patchpy-2.0.4.dist-info/licenses/LICENSE.txt
patchpy-2.0.4.dist-info/RECORD
