Metadata-Version: 2.3
Name: patchpy
Version: 2.0.4
Summary: A modern Python library for patch file parsing (diff file parsing)
Project-URL: Homepage, https://github.com/MatthewScholefield/patchpy
Author-email: "Matthew D. Scholefield" <matthew331199@gmail.com>
License: MIT
License-File: LICENSE.txt
Requires-Python: >=3.9
Requires-Dist: more-itertools>=10.2.0
